README.rst
setup.py
picklesize/__init__.py
picklesize/_numpysupport.py
picklesize/_picklesize.py
picklesize/test_picklesize.py
picklesize.egg-info/PKG-INFO
picklesize.egg-info/SOURCES.txt
picklesize.egg-info/dependency_links.txt
picklesize.egg-info/top_level.txt