Metadata-Version: 1.0
Name: picklesize
Version: 0.1.0
Summary: Calculates the pickled size of an object
Home-page: https://github.com/smurn/picklesize
Author: Stefan C. Mueller
Author-email: scm@smurn.org
License: UNKNOWN
Platform: UNKNOWN
